goda/__init__.py
goda/cleaner/__init__.py
goda/collector/__init__.py
goda/standard/__init__.py
goda-0.0.1.dist-info/LICENSE
goda-0.0.1.dist-info/METADATA
goda-0.0.1.dist-info/WHEEL
goda-0.0.1.dist-info/top_level.txt
goda-0.0.1.dist-info/RECORD
