Metadata-Version: 2.1
Name: goda
Version: 0.0.1
Summary: Python library to work with government open data
Home-page: https://github.com/Charles-Darwing-Data-Community/goda
Author: Pablo Sierra
Author-email: pavelsjo@gmail.com
License: UNKNOWN
Platform: UNKNOWN
Classifier: Programming Language :: Python :: 3
Classifier: License :: OSI Approved :: MIT License
Classifier: Operating System :: OS Independent
Requires-Python: >=3.6
